{
    "Label": "CPUSurplusCreditBalance",
    "Datapoints": [
        {
            "Timestamp": "2026-06-22T10:46:00+00:00",
            "Average": 8.279992416666667,
            "Maximum": 8.279992416666667,
            "Unit": "Count"
        },
        {
            "Timestamp": "2026-06-22T10:51:00+00:00",
            "Average": 9.770100383333334,
            "Maximum": 9.770100383333334,
            "Unit": "Count"
        },
        {
            "Timestamp": "2026-06-22T10:56:00+00:00",
            "Average": 11.00454795,
            "Maximum": 11.00454795,
            "Unit": "Count"
        }
    ]
}
